llm_prompting_gen/__about__.py
llm_prompting_gen/__init__.py
llm_prompting_gen/constants.py
llm_prompting_gen/generators.py
llm_prompting_gen/models/__init__.py
llm_prompting_gen/models/output.py
llm_prompting_gen/models/prompt_engineering.py
llm_prompting_gen/output_parser/__init__.py
llm_prompting_gen/output_parser/pydantic_parser.py
llm_prompting_gen-0.1.11.dist-info/METADATA
llm_prompting_gen-0.1.11.dist-info/WHEEL
llm_prompting_gen-0.1.11.dist-info/licenses/LICENSE.txt
llm_prompting_gen-0.1.11.dist-info/RECORD
