Metadata-Version: 2.1
Name: llm-prompting-gen
Version: 0.1.11
Project-URL: Documentation, https://github.com/FloTeu/llm-prompt-engineering-generator#readme
Project-URL: Issues, https://github.com/FloTeu/llm-prompt-engineering-generator/issues
Project-URL: Source, https://github.com/FloTeu/llm-prompt-engineering-generator
Author-email: fteutsch <florian.teutsch@inovex.de>
License-Expression: MIT
License-File: LICENSE.txt
Classifier: Development Status :: 4 - Beta
Classifier: Programming Language :: Python
Classifier: Programming Language :: Python :: 3.7
Classifier: Programming Language :: Python :: 3.8
Classifier: Programming Language :: Python :: 3.9
Classifier: Programming Language :: Python :: 3.10
Classifier: Programming Language :: Python :: 3.11
Classifier: Programming Language :: Python :: Implementation :: CPython
Classifier: Programming Language :: Python :: Implementation :: PyPy
Requires-Python: >=3.7
Requires-Dist: langchain==0.*
Requires-Dist: pydantic==2.*
